.gitignore
.pre-commit-config.yaml
COPYING.md
LICENSE.md
MANIFEST.in
README.md
bump_identify.py
pyproject.toml
setup.py
sync.py
.github/dependabot.yml
.github/workflows/ci.yml
.github/workflows/pypi.yml
precommend/.pre-commit-config.yaml
precommend/__init__.py
precommend/__main__.py
precommend/_version.py
precommend/core.py
precommend/rules.py
precommend.egg-info/PKG-INFO
precommend.egg-info/SOURCES.txt
precommend.egg-info/dependency_links.txt
precommend.egg-info/entry_points.txt
precommend.egg-info/requires.txt
precommend.egg-info/top_level.txt
tests/__init__.py
tests/conftest.py
tests/test_core.py
tests/data/cpp/CMakeLists.txt
tests/data/cpp/test.cpp
tests/data/generic/.readthedocs.yml
tests/data/generic/.github/dependabot.yml
tests/data/generic/.github/workflows/ci.yml
tests/data/python/foo.py
tests/data/python/pyproject.toml