Metadata-Version: 2.2
Name: precommend
Version: 0.3.9
Summary: Opinionated initialization of pre-commit configurations
Maintainer-email: Dominic Kempf <ssc@iwr.uni-heidelberg.de>
License: MIT
Classifier: Programming Language :: Python :: 3
Classifier: Operating System :: OS Independent
Classifier: License :: OSI Approved :: MIT License
Requires-Python: >=3.8
License-File: LICENSE.md
License-File: COPYING.md
Requires-Dist: click
Requires-Dist: identify>=2.5.36
Requires-Dist: pre-commit>=3.7.1
Requires-Dist: ruamel.yaml
Provides-Extra: tests
Requires-Dist: pytest; extra == "tests"
